celox/__init__.py
celox/abc.py
celox/client.py
celox/connection.py
celox/cookiejar.py
celox/defaults.py
celox/exceptions.py
celox/parser.py
celox/proxy.py
celox/py.typed
celox/request.py
celox/response.py
celox/timeout.py
celox/typedefs.py
celox/util.py
tests/__init__.py
tests/conftest.py
tests/test_client.py
tests/test_connection.py
tests/test_httpconnection.py
tests/test_parser.py
tests/test_proxy.py
tests/test_response.py
tests/test_util.py
celox-0.0.5.dist-info/LICENSE
celox-0.0.5.dist-info/METADATA
celox-0.0.5.dist-info/WHEEL
celox-0.0.5.dist-info/top_level.txt
celox-0.0.5.dist-info/RECORD
