Metadata-Version: 2.1
Name: celox
Version: 0.0.5
Summary: Fast, minimalistic HTTP client using trio.
Home-page: https://github.com/418Coffee/celox
Author: 418Coffee
Author-email: 418Coffee@cartinese.com
License: MIT
Project-URL: Bug Tracker, https://github.com/418Coffee/celox/issues
Classifier: Programming Language :: Python :: 3 :: Only
Classifier: Programming Language :: Python :: 3.8
Classifier: Programming Language :: Python :: 3.9
Classifier: Framework :: Trio
Classifier: License :: OSI Approved :: MIT License
Classifier: Operating System :: OS Independent
Requires-Python: >=3.8
License-File: LICENSE
Requires-Dist: trio (>=0.20.0)
Requires-Dist: attrs (>=21.4.0)
Requires-Dist: multidict (>=4.7.6)
Requires-Dist: yarl (>=1.6.3)
Requires-Dist: typing-extensions (>=4.1.1)
